MANIFEST.in
README.md
setup.py
buty_full/__init__.py
buty_full/__main__.py
buty_full.egg-info/PKG-INFO
buty_full.egg-info/SOURCES.txt
buty_full.egg-info/dependency_links.txt
buty_full.egg-info/entry_points.txt
buty_full.egg-info/top_level.txt
buty_full/data/.DS_Store
buty_full/data/.Rhistory
buty_full/data/Butyrate_summary.txt
buty_full/data/Complete_genome_16S.fasta
buty_full/data/Complete_genomes.txt
buty_full/data/Genome_NR.txt
buty_full/data/Genome_NR_nap_nar.txt
buty_full/data/Genome_NR_nir.txt
buty_full/data/Genome_SRB.txt
buty_full/data/Genome_SRB_SAT.txt
buty_full/data/Genome_SRB_arp.txt
buty_full/data/Genome_SRB_dsr_dsv.txt
buty_full/data/Genome_butyrate_Ato.txt
buty_full/data/Genome_butyrate_buk_ptb.txt
buty_full/data/Genome_butyrate_buk_ptbANDbut.txt
buty_full/data/Genome_butyrate_buk_ptbORbut.txt
buty_full/data/Genome_butyrate_but.txt
buty_full/data/assembly_summary_genbank_taxon.txt.notnormalized2.new.pathogen.habitat.8000.txt
buty_full/example/example.otu_seqs
buty_full/example/example.otu_table
buty_full/scripts/.DS_Store
buty_full/scripts/Bayers.model.py
buty_full/scripts/OTU.filter.py
buty_full/scripts/inferTraits.py
buty_full/scripts/treeformat.py